Workbook

Sheet Business Information
B1: Forecast Assumptions | Business Information
B3: How to use this workbook
B4: This business information was used to build the completed Forecast Assumptions tab in Task 1. For this task, use the completed assumptions as the inputs for your P&L Forecast. Do not re-enter assumptions directly into the P&L when they can be linked from the assumptions worksheet.
B6: Revenue
B7: Product | C7: FY2026E starting units | D7: FY2026E avg. sale price | E7: Forecast rule
B8: Baked Goods | C8: 100000 | D8: 4 | E8: From FY2027E, unit growth is 10%. Reduce the growth rate by 1 percentage point each year thereafter (9%, 8%, 7%). Average sale price grows 4% per year from FY2027E.
B9: Frozen Desserts | C9: 60000 | D9: 3 | E9: From FY2027E, unit growth is 10%. Reduce the growth rate by 1 percentage point each year thereafter (9%, 8%, 7%). Average sale price grows 4% per year from FY2027E.
B10: Beverages | C10: 50000 | D10: 2.5 | E10: From FY2027E, unit growth is 10%. Reduce the growth rate by 1 percentage point each year thereafter (9%, 8%, 7%). Average sale price grows 4% per year from FY2027E.
B12: Costs
B13: Driver | C13: FY2026E starting value | D13: Unit | E13: Forecast rule
B14: COGS per Baked Good | C14: 1.5 | D14: $ per unit | E14: Increase by 2% per year from FY2027E.
B15: COGS per Frozen Dessert | C15: 0.8 | D15: $ per unit | E15: Increase by 2% per year from FY2027E.
B16: COGS per Beverage | C16: 1.1 | D16: $ per unit | E16: Increase by 2% per year from FY2027E.
B17: Staff Costs | C17: 150000 | D17: $ | E17: Increase by 5% per year from FY2027E.
B18: Occupancy Costs | C18: 60000 | D18: $ | E18: Increase by 3% per year from FY2027E.
B19: Marketing Costs | C19: 10000 | D19: $ | E19: Increase by 5% per year from FY2027E.
B20: Other Operating Costs | C20: 5000 | D20: $ | E20: Increase by 5% per year from FY2027E.
B21: Annual D&A | C21: -0.05 | D21: % of revenue | E21: Increase by 0.25 percentage points each year (for example, -5.00% becomes -4.75% in FY2027E).
B23: Cash Flow
B24: Driver | C24: Starting value | D24: Unit | E24: Forecast rule
B25: Capital Expenditure (CapEx) | C25: Linked to D&A | D25: % of revenue | E25: Set CapEx equal to the Annual D&A percentage in each forecast year.
B26: Change in Net Working Capital (NWC) | C26: -0.01 | D26: % of revenue | E26: Use -1.0% of revenue in every forecast year.
B27: Dividend Payout Ratio | C27: 0.6 | D27: % | E27: Use 60.0% in every forecast year.
B29: Other
B30: Driver | C30: Starting value | D30: Unit | E30: Forecast rule
B31: Tax Rate | C31: 0.21 | D31: % | E31: Use 21.0% in every forecast year.
B32: Debt Interest Rate | C32: 0.04 | D32: % | E32: Use 4.0% in every forecast year.
B33: Cash Interest Rate | C33: 0.01 | D33: % | E33: Use 1.0% in every forecast year.

Sheet Forecast Assumptions
B1: Forecast Assumptions
B2: This worksheet contains the completed forecast assumptions from Task 1. Use these values as inputs for the P&L Forecast and link to them rather than retyping them.
B4: Driver | C4: Unit | D4: FY2026E | E4: FY2027E | F4: FY2028E | G4: FY2029E | H4: FY2030E
B6: Revenue
B7: Baked Goods
B8: Number of Units Sold | C8: # | D8: 100000 | E8: =D8*(1+10%) -> 110000 | F8: =E8*(1+9%) -> 119900 | G8: =F8*(1+8%) -> 129492 | H8: =G8*(1+7%) -> 138556.44
B9: Average Sale Price | C9: $ | D9: 4 | E9: =D9*(1+4%) -> 4.16 | F9: =E9*(1+4%) -> 4.3264 | G9: =F9*(1+4%) -> 4.499456 | H9: =G9*(1+4%) -> 4.6794342
B10: Frozen Desserts
B11: Number of Units Sold | C11: # | D11: 60000 | E11: =D11*(1+10%) -> 66000 | F11: =E11*(1+9%) -> 71940 | G11: =F11*(1+8%) -> 77695.2 | H11: =G11*(1+7%) -> 83133.864
B12: Average Sale Price | C12: $ | D12: 3 | E12: =D12*(1+4%) -> 3.12 | F12: =E12*(1+4%) -> 3.2448 | G12: =F12*(1+4%) -> 3.374592 | H12: =G12*(1+4%) -> 3.5095757
B13: Beverages
B14: Number of Units Sold | C14: # | D14: 50000 | E14: =D14*(1+10%) -> 55000 | F14: =E14*(1+9%) -> 59950 | G14: =F14*(1+8%) -> 64746 | H14: =G14*(1+7%) -> 69278.22
B15: Average Sale Price | C15: $ | D15: 2.5 | E15: =D15*(1+4%) -> 2.6 | F15: =E15*(1+4%) -> 2.704 | G15: =F15*(1+4%) -> 2.81216 | H15: =G15*(1+4%) -> 2.9246464
B17: Costs
B18: Cost of Goods Sold (COGS)
B19: COGS per Baked Good | C19: $ per unit | D19: 1.5 | E19: =D19*(1+0.02) -> 1.53 | F19: =E19*(1+0.02) -> 1.5606 | G19: =F19*(1+0.02) -> 1.591812 | H19: =G19*(1+0.02) -> 1.6236482
B20: COGS per Frozen Dessert | C20: $ per unit | D20: 0.8 | E20: =D20*(1+0.02) -> 0.816 | F20: =E20*(1+0.02) -> 0.83232 | G20: =F20*(1+0.02) -> 0.8489664 | H20: =G20*(1+0.02) -> 0.86594573
B21: COGS per Beverage | C21: $ per unit | D21: 1.1 | E21: =D21*(1+0.02) -> 1.122 | F21: =E21*(1+0.02) -> 1.14444 | G21: =F21*(1+0.02) -> 1.1673288 | H21: =G21*(1+0.02) -> 1.1906754
B22: Operating Expenses (OpEx)
B23: Staff Costs | C23: $ | D23: 150000 | E23: =D23*(1+0.05) -> 157500 | F23: =E23*(1+0.05) -> 165375 | G23: =F23*(1+0.05) -> 173643.75 | H23: =G23*(1+0.05) -> 182325.94
B24: Occupancy Costs | C24: $ | D24: 60000 | E24: =D24*(1+0.03) -> 61800 | F24: =E24*(1+0.03) -> 63654 | G24: =F24*(1+0.03) -> 65563.62 | H24: =G24*(1+0.03) -> 67530.529
B25: Marketing Costs | C25: $ | D25: 10000 | E25: =D25*(1+0.05) -> 10500 | F25: =E25*(1+0.05) -> 11025 | G25: =F25*(1+0.05) -> 11576.25 | H25: =G25*(1+0.05) -> 12155.062
B26: Other Operating Costs | C26: $ | D26: 5000 | E26: =D26*(1+0.05) -> 5250 | F26: =E26*(1+0.05) -> 5512.5 | G26: =F26*(1+0.05) -> 5788.125 | H26: =G26*(1+0.05) -> 6077.5312
B27: Depreciation & Amortization (D&A)
B28: Annual D&A | C28: % of revenue | D28: -0.05 | E28: =D28+0.0025 -> -0.0475 | F28: =E28+0.0025 -> -0.045 | G28: =F28+0.0025 -> -0.0425 | H28: =G28+0.0025 -> -0.04
B30: Cash Flow
B31: Capital Expenditure (CapEx) | C31: % of revenue | D31: =D28 -> -0.05 | E31: =E28 -> -0.0475 | F31: =F28 -> -0.045 | G31: =G28 -> -0.0425 | H31: =H28 -> -0.04
B32: Change in Net Working Capital (NWC) | C32: % of revenue | D32: -0.01 | E32: -0.01 | F32: -0.01 | G32: -0.01 | H32: -0.01
B33: Dividend Payout Ratio | C33: % | D33: 0.6 | E33: 0.6 | F33: 0.6 | G33: 0.6 | H33: 0.6
B35: Other
B36: Tax Rate | C36: % | D36: 0.21 | E36: 0.21 | F36: 0.21 | G36: 0.21 | H36: 0.21
B37: Debt Interest Rate | C37: % | D37: 0.04 | E37: 0.04 | F37: 0.04 | G37: 0.04 | H37: 0.04
B38: Cash Interest Rate | C38: % | D38: 0.01 | E38: 0.01 | F38: 0.01 | G38: 0.01 | H38: 0.01
B40: Tip: Check that percentages, dollar values, and unit counts use the correct number format before submitting your workbook.

Sheet Glossary
B1: Financial Modeling Glossary
B3: Term | C3: Definition
B4: Capital Expenditure (CapEx) | C4: Spending on long-term assets such as equipment, property, or technology that supports the business over multiple periods.
B5: Cost of Goods Sold (COGS) | C5: The direct costs associated with producing the goods or services sold by a business.
B6: Depreciation & Amortization (D&A) | C6: Non-cash expenses that allocate the cost of tangible and intangible assets over their useful lives.
B7: Dividend Payout Ratio | C7: The percentage of net profit distributed to shareholders as dividends.
B8: EBITDA | C8: Earnings before interest, taxes, depreciation, and amortization. It is commonly used as a measure of operating profitability before financing, tax, and non-cash D&A expenses.
B9: EBIT | C9: Earnings before interest and taxes. It represents operating profit after depreciation and amortization.
B10: Net Working Capital (NWC) | C10: A measure of short-term operating assets and liabilities. Changes in NWC can either use or release cash.
B11: Operating Expenses (OpEx) | C11: Ongoing costs of running the business that are not direct product costs, such as staff, occupancy, marketing, and administrative costs.
B12: Profit & Loss Statement (P&L) | C12: A financial statement that summarizes revenue, expenses, and profit or loss over a period of time.
B13: Working Capital | C13: The short-term resources needed to support day-to-day operations, including items such as receivables, inventory, and payables.

Sheet P&L Forecast
B1: P&L Forecast
B2: Complete every light-blue cell. Link forecast inputs to the Forecast Assumptions worksheet, then build the P&L calculations across FY2026E–FY2030E.
B4: P&L Line | C4: Unit | D4: FY2026E | E4: FY2027E | F4: FY2028E | G4: FY2029E | H4: FY2030E
B6: Revenue
B7: Baked Goods Revenue | C7: $ | D7: ='Forecast Assumptions'!D8*'Forecast Assumptions'!D9 -> 400000 | E7: ='Forecast Assumptions'!E8*'Forecast Assumptions'!E9 -> 457600 | F7: ='Forecast Assumptions'!F8*'Forecast Assumptions'!F9 -> 518735.36 | G7: ='Forecast Assumptions'!G8*'Forecast Assumptions'!G9 -> 582643.56 | H7: ='Forecast Assumptions'!H8*'Forecast Assumptions'!H9 -> 648365.75
B8: Frozen Desserts Revenue | C8: $ | D8: ='Forecast Assumptions'!D11*'Forecast Assumptions'!D12 -> 180000 | E8: ='Forecast Assumptions'!E11*'Forecast Assumptions'!E12 -> 205920 | F8: ='Forecast Assumptions'!F11*'Forecast Assumptions'!F12 -> 233430.91 | G8: ='Forecast Assumptions'!G11*'Forecast Assumptions'!G12 -> 262189.6 | H8: ='Forecast Assumptions'!H11*'Forecast Assumptions'!H12 -> 291764.59
B9: Beverages Revenue | C9: $ | D9: ='Forecast Assumptions'!D14*'Forecast Assumptions'!D15 -> 125000 | E9: ='Forecast Assumptions'!E14*'Forecast Assumptions'!E15 -> 143000 | F9: ='Forecast Assumptions'!F14*'Forecast Assumptions'!F15 -> 162104.8 | G9: ='Forecast Assumptions'!G14*'Forecast Assumptions'!G15 -> 182076.11 | H9: ='Forecast Assumptions'!H14*'Forecast Assumptions'!H15 -> 202614.3
B10: Total Revenue | C10: $ | D10: =SUM(D7:D9) -> 705000 | E10: =SUM(E7:E9) -> 806520 | F10: =SUM(F7:F9) -> 914271.07 | G10: =SUM(G7:G9) -> 1026909.3 | H10: =SUM(H7:H9) -> 1142744.6
B11: Revenue Growth | C11: % | D11: — | E11: =E10/D10-1 -> 0.144 | F11: =F10/E10-1 -> 0.1336 | G11: =G10/F10-1 -> 0.1232 | H11: =H10/G10-1 -> 0.1128
B13: Cost of Goods Sold
B14: Baked Goods COGS | C14: $ | D14: ='Forecast Assumptions'!D8*'Forecast Assumptions'!D19 -> 150000 | E14: ='Forecast Assumptions'!E8*'Forecast Assumptions'!E19 -> 168300 | F14: ='Forecast Assumptions'!F8*'Forecast Assumptions'!F19 -> 187115.94 | G14: ='Forecast Assumptions'!G8*'Forecast Assumptions'!G19 -> 206126.92 | H14: ='Forecast Assumptions'!H8*'Forecast Assumptions'!H19 -> 224966.92
B15: Frozen Desserts COGS | C15: $ | D15: ='Forecast Assumptions'!D11*'Forecast Assumptions'!D20 -> 48000 | E15: ='Forecast Assumptions'!E11*'Forecast Assumptions'!E20 -> 53856 | F15: ='Forecast Assumptions'!F11*'Forecast Assumptions'!F20 -> 59877.101 | G15: ='Forecast Assumptions'!G11*'Forecast Assumptions'!G20 -> 65960.614 | H15: ='Forecast Assumptions'!H11*'Forecast Assumptions'!H20 -> 71989.414
B16: Beverages COGS | C16: $ | D16: ='Forecast Assumptions'!D14*'Forecast Assumptions'!D21 -> 55000 | E16: ='Forecast Assumptions'!E14*'Forecast Assumptions'!E21 -> 61710 | F16: ='Forecast Assumptions'!F14*'Forecast Assumptions'!F21 -> 68609.178 | G16: ='Forecast Assumptions'!G14*'Forecast Assumptions'!G21 -> 75579.87 | H16: ='Forecast Assumptions'!H14*'Forecast Assumptions'!H21 -> 82487.871
B17: Total Cost of Goods Sold | C17: $ | D17: =SUM(D14:D16) -> 253000 | E17: =SUM(E14:E16) -> 283866 | F17: =SUM(F14:F16) -> 315602.22 | G17: =SUM(G14:G16) -> 347667.4 | H17: =SUM(H14:H16) -> 379444.2
B19: Gross Profit | C19: $ | D19: =D10-D17 -> 452000 | E19: =E10-E17 -> 522654 | F19: =F10-F17 -> 598668.85 | G19: =G10-G17 -> 679241.86 | H19: =H10-H17 -> 763300.43
B20: Gross Margin | C20: % | D20: =D19/D10 -> 0.64113475 | E20: =E19/E10 -> 0.64803601 | F20: =F19/F10 -> 0.65480454 | G20: =G19/G10 -> 0.66144292 | H20: =H19/H10 -> 0.66795363
B22: Operating Expenses
B23: Staff Costs | C23: $ | D23: ='Forecast Assumptions'!D23 -> 150000 | E23: ='Forecast Assumptions'!E23 -> 157500 | F23: ='Forecast Assumptions'!F23 -> 165375 | G23: ='Forecast Assumptions'!G23 -> 173643.75 | H23: ='Forecast Assumptions'!H23 -> 182325.94
B24: Occupancy Costs | C24: $ | D24: ='Forecast Assumptions'!D24 -> 60000 | E24: ='Forecast Assumptions'!E24 -> 61800 | F24: ='Forecast Assumptions'!F24 -> 63654 | G24: ='Forecast Assumptions'!G24 -> 65563.62 | H24: ='Forecast Assumptions'!H24 -> 67530.529
B25: Marketing Costs | C25: $ | D25: ='Forecast Assumptions'!D25 -> 10000 | E25: ='Forecast Assumptions'!E25 -> 10500 | F25: ='Forecast Assumptions'!F25 -> 11025 | G25: ='Forecast Assumptions'!G25 -> 11576.25 | H25: ='Forecast Assumptions'!H25 -> 12155.062
B26: Other Operating Costs | C26: $ | D26: ='Forecast Assumptions'!D26 -> 5000 | E26: ='Forecast Assumptions'!E26 -> 5250 | F26: ='Forecast Assumptions'!F26 -> 5512.5 | G26: ='Forecast Assumptions'!G26 -> 5788.125 | H26: ='Forecast Assumptions'!H26 -> 6077.5312
B27: Total Operating Expenses | C27: $ | D27: =SUM(D23:D26) -> 225000 | E27: =SUM(E23:E26) -> 235050 | F27: =SUM(F23:F26) -> 245566.5 | G27: =SUM(G23:G26) -> 256571.74 | H27: =SUM(H23:H26) -> 268089.06
B29: EBITDA | C29: $ | D29: =D19-D27 -> 227000 | E29: =E19-E27 -> 287604 | F29: =F19-F27 -> 353102.35 | G29: =G19-G27 -> 422670.12 | H29: =H19-H27 -> 495211.37
B30: EBITDA Margin | C30: % | D30: =D29/D10 -> 0.32198582 | E30: =E29/E10 -> 0.35659872 | F30: =F29/F10 -> 0.38621188 | G30: =G29/G10 -> 0.41159441 | H30: =H29/H10 -> 0.43335261
B32: Profit After D&A, Interest and Tax
B33: Depreciation & Amortization | C33: $ | D33: =-'Forecast Assumptions'!D28*D10 -> 35250 | E33: =-'Forecast Assumptions'!E28*E10 -> 38309.7 | F33: =-'Forecast Assumptions'!F28*F10 -> 41142.198 | G33: =-'Forecast Assumptions'!G28*G10 -> 43643.644 | H33: =-'Forecast Assumptions'!H28*H10 -> 45709.785
B34: EBIT | C34: $ | D34: =D29-D33 -> 191750 | E34: =E29-E33 -> 249294.3 | F34: =F29-F33 -> 311960.15 | G34: =G29-G33 -> 379026.47 | H34: =H29-H33 -> 449501.58
B36: Temporary Net Interest Expense | C36: $ | D36: 15850 | E36: 15850 | F36: 15850 | G36: 15850 | H36: 15850
B37: Profit Before Tax | C37: $ | D37: =D34-D36 -> 175900 | E37: =E34-E36 -> 233444.3 | F37: =F34-F36 -> 296110.15 | G37: =G34-G36 -> 363176.47 | H37: =H34-H36 -> 433651.58
B38: Tax Expense | C38: $ | D38: =D37*'Forecast Assumptions'!D36 -> 36939 | E38: =E37*'Forecast Assumptions'!E36 -> 49023.303 | F38: =F37*'Forecast Assumptions'!F36 -> 62183.133 | G38: =G37*'Forecast Assumptions'!G36 -> 76267.06 | H38: =H37*'Forecast Assumptions'!H36 -> 91066.833
B39: Net Profit | C39: $ | D39: =D37-D38 -> 138961 | E39: =E37-E38 -> 184421 | F39: =F37-F38 -> 233927.02 | G39: =G37-G38 -> 286909.42 | H39: =H37-H38 -> 342584.75
B42: Temporary Net Interest Expense is provided for Task 2 so you can complete Profit Before Tax, Tax Expense, and Net Profit. In Task 3, you will replace this placeholder with interest calculated from the cash and debt forecast.
B44: Modeling key
B45: Light-blue cells | C45: Complete these cells.
B46: Green text | C46: Use a formula that links to another worksheet.
B47: Black text | C47: Use a formula calculated within the P&L.
B48: Blue text / yellow fill | C48: Provided task input; use it as given in Task 2.
B50: Tip: Link assumptions rather than retyping them. Check that your formulas extend across all five forecast years. In this P&L, expense lines are shown as positive amounts and subtracted when calculating profit subtotals.
